{
  "id": 331,
  "image": "furrypfp331",
  "name": "RiverClaw4399",
  "age": 32,
  "gender": "male",
  "pronouns": "he/him",
  "location": "Pawston",
  "species": "Dog",
  "fur_color": "golden",
  "tail_type": "short",
  "activities": [
    "Streaming",
    "Dancing",
    "Cooking"
  ],
  "personality_traits": [
    "shy",
    "playful",
    "adventurous"
  ],
  "bio": "Hi! I'm RiverClaw4399, a golden Dog from Pawston. I enjoy Streaming, Dancing, Cooking. Friends describe me as shy, playful, adventurous. My short tail is always wagging when I'm having fun!"
}