{
  "id": 311,
  "image": "furrypfp311",
  "name": "NightFang6417",
  "age": 28,
  "gender": "non-binary",
  "pronouns": "they/them",
  "location": "Furryville",
  "species": "Raccoon",
  "fur_color": "golden",
  "tail_type": "thin",
  "activities": [
    "Drawing",
    "Cooking",
    "Reading"
  ],
  "personality_traits": [
    "playful",
    "shy",
    "adventurous"
  ],
  "bio": "Hi! I'm NightFang6417, a golden Raccoon from Furryville. I enjoy Drawing, Cooking, Reading. Friends describe me as playful, shy, adventurous. My thin tail is always wagging when I'm having fun!"
}