{
  "id": 386,
  "image": "furrypfp386",
  "name": "RiverClaw5895",
  "age": 33,
  "gender": "non-binary",
  "pronouns": "they/them",
  "location": "Tailtown",
  "species": "Rabbit",
  "fur_color": "striped",
  "tail_type": "thin",
  "activities": [
    "Cosplay",
    "Reading",
    "Hiking"
  ],
  "personality_traits": [
    "playful",
    "energetic",
    "adventurous"
  ],
  "bio": "Hi! I'm RiverClaw5895, a striped Rabbit from Tailtown. I enjoy Cosplay, Reading, Hiking. Friends describe me as playful, energetic, adventurous. My thin tail is always wagging when I'm having fun!"
}