{
  "id": 245,
  "image": "furrypfp245",
  "name": "EmberFang6313",
  "age": 28,
  "gender": "female",
  "pronouns": "she/her",
  "location": "Star Hollow",
  "species": "Dragon",
  "fur_color": "spotted",
  "tail_type": "thin",
  "activities": [
    "Reading",
    "Music",
    "Dancing"
  ],
  "personality_traits": [
    "shy",
    "creative",
    "chill"
  ],
  "bio": "Hi! I'm EmberFang6313, a spotted Dragon from Star Hollow. I enjoy Reading, Music, Dancing. Friends describe me as shy, creative, chill. My thin tail is always wagging when I'm having fun!"
}