{
  "id": 387,
  "image": "furrypfp387",
  "name": "FluffyFox8896",
  "age": 32,
  "gender": "female",
  "pronouns": "she/her",
  "location": "Pawston",
  "species": "Rabbit",
  "fur_color": "spotted",
  "tail_type": "feathered",
  "activities": [
    "Hiking",
    "Dancing",
    "Cosplay"
  ],
  "personality_traits": [
    "curious",
    "adventurous",
    "creative"
  ],
  "bio": "Hi! I'm FluffyFox8896, a spotted Rabbit from Pawston. I enjoy Hiking, Dancing, Cosplay. Friends describe me as curious, adventurous, creative. My feathered tail is always wagging when I'm having fun!"
}