{
  "id": 192,
  "image": "furrypfp192",
  "name": "EmberFang1710",
  "age": 21,
  "gender": "non-binary",
  "pronouns": "they/them",
  "location": "Howl City",
  "species": "Cat",
  "fur_color": "striped",
  "tail_type": "curly",
  "activities": [
    "Dancing",
    "Drawing",
    "Reading"
  ],
  "personality_traits": [
    "friendly",
    "adventurous",
    "energetic"
  ],
  "bio": "Hi! I'm EmberFang1710, a striped Cat from Howl City. I enjoy Dancing, Drawing, Reading. Friends describe me as friendly, adventurous, energetic. My curly tail is always wagging when I'm having fun!"
}