{
  "id": 313,
  "image": "furrypfp313",
  "name": "SilverHowl6024",
  "age": 32,
  "gender": "male",
  "pronouns": "he/him",
  "location": "Claw Harbor",
  "species": "Rabbit",
  "fur_color": "golden",
  "tail_type": "thin",
  "activities": [
    "Cosplay",
    "Cooking",
    "Streaming"
  ],
  "personality_traits": [
    "playful",
    "friendly",
    "creative"
  ],
  "bio": "Hi! I'm SilverHowl6024, a golden Rabbit from Claw Harbor. I enjoy Cosplay, Cooking, Streaming. Friends describe me as playful, friendly, creative. My thin tail is always wagging when I'm having fun!"
}